BIAS/Create_RF.py
BIAS/SB_Test_runner.py
BIAS/SB_Toolbox.py
BIAS/__init__.py
BIAS/install.r
BIAS/uniform_test.py
BIAS/models/empty.txt
BIAS/models/opt_cnn_model-100.keras
BIAS/models/opt_cnn_model-200.keras
BIAS/models/opt_cnn_model-30.keras
BIAS/models/opt_cnn_model-50.keras
BIAS/models/opt_cnn_model-500.keras
BIAS/models/opt_cnn_model-600.keras
BIAS/models/targetnames.npy
struct_bias-1.4.1.dist-info/LICENSE.md
struct_bias-1.4.1.dist-info/METADATA
struct_bias-1.4.1.dist-info/WHEEL
struct_bias-1.4.1.dist-info/top_level.txt
struct_bias-1.4.1.dist-info/RECORD
