Metadata-Version: 2.1
Name: struct-bias
Version: 1.4.1
Summary: BIAS toolbox: Structural bias detection for continuous optimization algorithms
Author: Diederick Vermetten, Niki van Stein
Author-email: d.l.vermetten@liacs.leidenuniv.nl
Classifier: Programming Language :: Python :: 3
Classifier: License :: OSI Approved :: MIT License
Classifier: Operating System :: OS Independent
Requires-Python: >=3.6
License-File: LICENSE.md
Requires-Dist: numpy
Requires-Dist: tensorflow
Requires-Dist: shap
Requires-Dist: rpy2
Requires-Dist: scipy
Requires-Dist: pandas
Requires-Dist: scikit-learn
Requires-Dist: matplotlib
Requires-Dist: seaborn
Requires-Dist: statsmodels
Requires-Dist: regex
Requires-Dist: autokeras
